panguvan/.env.config
panguvan/__init__.py
panguvan/data/__init__.py
panguvan/data/base.py
panguvan/data/ise.py
panguvan/db.py
panguvan/models/__init__.py
panguvan/models/ise.py
panguvan/models/tgju.py
panguvan/utils/__init__.py
panguvan/utils/jdate.py
panguvan-0.1.6.dist-info/METADATA
panguvan-0.1.6.dist-info/WHEEL
panguvan-0.1.6.dist-info/RECORD
