Metadata-Version: 2.1
Name: panguvan
Version: 0.1.6
Summary: 
Home-page: https://github.com/yghaderi/panguvan
Author: Yaghoub Ghadri
Author-email: y.ghaderi@outlook.com
Requires-Python: >=3.10,<4.0
Classifier: Programming Language :: Python :: 3
Classifier: Programming Language :: Python :: 3.10
Classifier: Programming Language :: Python :: 3.11
Project-URL: Repository, https://github.com/yghaderi/panguvan
